iplookupx/__init__.py
iplookupx/utils.py
iplookupx-0.1.2.dist-info/licenses/LICENSE
iplookupx-0.1.2.dist-info/METADATA
iplookupx-0.1.2.dist-info/WHEEL
iplookupx-0.1.2.dist-info/top_level.txt
iplookupx-0.1.2.dist-info/RECORD
