Metadata-Version: 2.4
Name: iplookupx
Version: 0.1.2
Summary: A Python package to fetch public and local IP information, and to make HTTP requests with proxy support, including HTML content fetching via requests or Selenium.
Author: Ramesh Chandra
Author-email: rameshsofter@gmail.com
Classifier: Programming Language :: Python :: 3
Classifier: License :: OSI Approved :: MIT License
Classifier: Operating System :: OS Independent
Requires-Python: >=3.6
License-File: LICENSE
Requires-Dist: requests
Dynamic: author
Dynamic: author-email
Dynamic: classifier
Dynamic: description
Dynamic: description-content-type
Dynamic: license-file
Dynamic: requires-dist
Dynamic: requires-python
Dynamic: summary
